tonyear/__init__.py
tonyear/core.py
tonyear/ghgforcing.py
tonyear/tests/__init__.py
tonyear/tests/test_tonyear.py
tonyear-1.1.0.dist-info/LICENSE
tonyear-1.1.0.dist-info/METADATA
tonyear-1.1.0.dist-info/WHEEL
tonyear-1.1.0.dist-info/top_level.txt
tonyear-1.1.0.dist-info/RECORD
