Metadata-Version: 2.1
Name: tonyear
Version: 1.1.0
Summary: exploring ton-year accounting methods
Home-page: https://github.com/carbonplan/ton-year
Maintainer: Freya Chay
Maintainer-email: freya@carbonplan.org
License: MIT
Keywords: carbon,climate,tonyear
Platform: UNKNOWN
Requires-Python: >=3.8
Requires-Dist: numpy
Requires-Dist: pandas
Requires-Dist: scipy
